pms/__init__.py
pms/__main__.py
pms/db_functions.py
pms/models.py
pms/password_controller.py
pms/user_controller.py
pms/utility_functions.py
password_management_system-1.0.1.dist-info/METADATA
password_management_system-1.0.1.dist-info/WHEEL
password_management_system-1.0.1.dist-info/entry_points.txt
password_management_system-1.0.1.dist-info/top_level.txt
password_management_system-1.0.1.dist-info/RECORD
