Metadata-Version: 2.1
Name: password-management-system
Version: 1.0.1
Summary: password management system through cli
Keywords: cli
Classifier: License :: OSI Approved :: MIT License
Classifier: Programming Language :: Python
Classifier: Programming Language :: Python :: 3
Requires-Python: >=3.9
Requires-Dist: cryptography (>=40.0.2)
Provides-Extra: dev
Requires-Dist: pytest ; extra == 'dev'
